waybackpack/__init__.py
waybackpack/asset.py
waybackpack/cdx.py
waybackpack/cli.py
waybackpack/pack.py
waybackpack/session.py
waybackpack/settings.py
waybackpack/version.py
waybackpack-0.6.4.dist-info/LICENSE.txt
waybackpack-0.6.4.dist-info/METADATA
waybackpack-0.6.4.dist-info/WHEEL
waybackpack-0.6.4.dist-info/entry_points.txt
waybackpack-0.6.4.dist-info/top_level.txt
waybackpack-0.6.4.dist-info/RECORD
