Metadata-Version: 2.1
Name: waybackpack
Version: 0.6.4
Summary: Command-line tool that lets you download the entire Wayback Machine archive for a given URL.
Home-page: https://github.com/jsvine/waybackpack
Author: Jeremy Singer-Vine
Author-email: jsvine@gmail.com
License: MIT
Keywords: wayback machine archive
Classifier: Development Status :: 3 - Alpha
Classifier: Intended Audience :: Developers
Classifier: License :: OSI Approved :: MIT License
Classifier: Operating System :: OS Independent
Classifier: Programming Language :: Python :: 3.3
Classifier: Programming Language :: Python :: 3.4
Classifier: Programming Language :: Python :: 3.5
Classifier: Programming Language :: Python :: 3.6
Classifier: Programming Language :: Python :: 3.7
Classifier: Programming Language :: Python :: 3.8
Classifier: Programming Language :: Python :: 3.9
Classifier: Programming Language :: Python :: 3.10
Classifier: Programming Language :: Python :: 3.11
Classifier: Programming Language :: Python :: 3.12
License-File: LICENSE.txt
Requires-Dist: requests
Provides-Extra: full
Requires-Dist: tqdm ; extra == 'full'
